{
  "project_info": {
    "project_number": "71677607018",
    "firebase_url": "https://appfillbelly-8494d.firebaseio.com",
    "project_id": "appfillbelly-8494d",
    "storage_bucket": "appfillbelly-8494d.appspot.com"
  },
  "client": [
    {
      "client_info": {
        "mobilesdk_app_id": "1:71677607018:android:45ae3901df112115",
        "android_client_info": {
          "package_name": "com.example.jay.appfillbelly"
        }
      },
      "oauth_client": [
        {
          "client_id": "71677607018-a0gh54jivu6psb5683licib05pr059b1.apps.googleusercontent.com",
          "client_type": 3
        }
      ],
      "api_key": [
        {
          "current_key": "AIzaSyAa8ItMElzlciEUWEEuEpL2umrIQtFWquA"
        }
      ],
      "services": {
        "analytics_service": {
          "status": 1
        },
        "appinvite_service": {
          "status": 1,
          "other_platform_oauth_client": []
        },
        "ads_service": {
          "status": 2
        }
      }
    }
  ],
  "configuration_version": "1"
}